gallica_autobib/__init__.py
gallica_autobib/cache.py
gallica_autobib/cli.py
gallica_autobib/gallipy/__init__.py
gallica_autobib/gallipy/__init__.pyi
gallica_autobib/gallipy/ark.py
gallica_autobib/gallipy/ark.pyi
gallica_autobib/gallipy/helpers.py
gallica_autobib/gallipy/helpers.pyi
gallica_autobib/gallipy/monadic.py
gallica_autobib/gallipy/monadic.pyi
gallica_autobib/gallipy/readme.md
gallica_autobib/gallipy/resource.py
gallica_autobib/gallipy/resource.pyi
gallica_autobib/models.py
gallica_autobib/parsers.py
gallica_autobib/pipeline.py
gallica_autobib/process.py
gallica_autobib/query.py
gallica_autobib/templates/article.bib
gallica_autobib/templates/book.bib
gallica_autobib/templates/collection.bib
gallica_autobib/templates/newspaperarticle.bib
gallica_autobib/templates/output.html
gallica_autobib/templates/output.org
gallica_autobib/templates/output.txt
gallica_autobib/templating.py
gallica_autobib/util.py
gallica_autobib-0.1.6.dist-info/entry_points.txt
gallica_autobib-0.1.6.dist-info/LICENSE
gallica_autobib-0.1.6.dist-info/WHEEL
gallica_autobib-0.1.6.dist-info/METADATA
gallica_autobib-0.1.6.dist-info/RECORD
